llama_index/packs/resume_screener/__init__.py
llama_index/packs/resume_screener/base.py
llama_index_packs_resume_screener-0.9.2.dist-info/METADATA
llama_index_packs_resume_screener-0.9.2.dist-info/WHEEL
llama_index_packs_resume_screener-0.9.2.dist-info/licenses/LICENSE
llama_index_packs_resume_screener-0.9.2.dist-info/RECORD
