Metadata-Version: 2.4
Name: llama-index-packs-resume-screener
Version: 0.9.2
Summary: llama-index packs resume_screener integration
Author-email: Your Name <you@example.com>
Maintainer: Disiok
License-Expression: MIT
License-File: LICENSE
Keywords: document,pdf,resume,structured output
Requires-Python: <4.0,>=3.9
Requires-Dist: llama-index-llms-openai<0.6,>=0.5.0
Requires-Dist: llama-index-readers-file<0.6,>=0.5.0
Requires-Dist: pypdf
